src/__init__.py
src/descriptor.py
src/metaclasses.py
src/server.py
src/utils.py
src/variables.py
chat_async_server-1.0.0.dist-info/METADATA
chat_async_server-1.0.0.dist-info/WHEEL
chat_async_server-1.0.0.dist-info/top_level.txt
chat_async_server-1.0.0.dist-info/RECORD
