Metadata-Version: 2.1
Name: chat-async-server
Version: 1.0.0
Summary: description
Author: Michael Kurashev
Author-email: kurashevmichael@gmail.com
Requires-Dist: alabaster (==0.7.13)
Requires-Dist: altgraph (==0.17.3)
Requires-Dist: Babel (==2.12.1)
Requires-Dist: bleach (==6.0.0)
Requires-Dist: certifi (==2023.5.7)
Requires-Dist: cffi (==1.15.1)
Requires-Dist: chardet (==5.1.0)
Requires-Dist: charset-normalizer (==3.1.0)
Requires-Dist: click (==8.1.3)
Requires-Dist: cryptography (==41.0.1)
Requires-Dist: cx-Freeze (==6.15.1)
Requires-Dist: decorator (==5.1.1)
Requires-Dist: dis (==1.0.1)
Requires-Dist: docutils (==0.20.1)
Requires-Dist: Faker (==18.3.4)
Requires-Dist: flake8 (==6.0.0)
Requires-Dist: greenlet (==2.0.2)
Requires-Dist: idna (==3.4)
Requires-Dist: imagesize (==1.4.1)
Requires-Dist: importlib-metadata (==6.6.0)
Requires-Dist: jaraco.classes (==3.2.3)
Requires-Dist: jeepney (==0.8.0)
Requires-Dist: Jinja2 (==3.1.2)
Requires-Dist: keyring (==23.13.1)
Requires-Dist: markdown-it-py (==3.0.0)
Requires-Dist: MarkupSafe (==2.1.3)
Requires-Dist: mccabe (==0.7.0)
Requires-Dist: mdurl (==0.1.2)
Requires-Dist: more-itertools (==9.1.0)
Requires-Dist: packaging (==23.1)
Requires-Dist: patchelf (==0.17.2.1)
Requires-Dist: pkginfo (==1.9.6)
Requires-Dist: pycodestyle (==2.10.0)
Requires-Dist: pycparser (==2.21)
Requires-Dist: pycryptodome (==3.18.0)
Requires-Dist: pyflakes (==3.0.1)
Requires-Dist: Pygments (==2.15.1)
Requires-Dist: pyinstaller (==5.10.1)
Requires-Dist: pyinstaller-hooks-contrib (==2023.2)
Requires-Dist: PyQt5 (==5.15.9)
Requires-Dist: pyqt5-plugins (==5.15.9.2.3)
Requires-Dist: PyQt5-Qt5 (==5.15.2)
Requires-Dist: PyQt5-sip (==12.11.1)
Requires-Dist: pyqt5-tools (==5.15.9.3.3)
Requires-Dist: python-dateutil (==2.8.2)
Requires-Dist: python-dotenv (==1.0.0)
Requires-Dist: PyYAML (==6.0)
Requires-Dist: qt5-applications (==5.15.2.2.3)
Requires-Dist: qt5-tools (==5.15.2.1.3)
Requires-Dist: readme-renderer (==37.3)
Requires-Dist: requests (==2.31.0)
Requires-Dist: requests-toolbelt (==1.0.0)
Requires-Dist: rfc3986 (==2.0.0)
Requires-Dist: rich (==13.4.2)
Requires-Dist: SecretStorage (==3.3.3)
Requires-Dist: self (==2020.12.3)
Requires-Dist: six (==1.16.0)
Requires-Dist: snowballstemmer (==2.2.0)
Requires-Dist: Sphinx (==7.0.1)
Requires-Dist: sphinxcontrib-applehelp (==1.0.4)
Requires-Dist: sphinxcontrib-devhelp (==1.0.2)
Requires-Dist: sphinxcontrib-htmlhelp (==2.0.1)
Requires-Dist: sphinxcontrib-jsmath (==1.0.1)
Requires-Dist: sphinxcontrib-qthelp (==1.0.3)
Requires-Dist: sphinxcontrib-serializinghtml (==1.1.5)
Requires-Dist: SQLAlchemy (==2.0.9)
Requires-Dist: SQLAlchemy-Utils (==0.40.0)
Requires-Dist: tabulate (==0.9.0)
Requires-Dist: twine (==4.0.2)
Requires-Dist: typing-extensions (==4.5.0)
Requires-Dist: urllib3 (==2.0.3)
Requires-Dist: webencodings (==0.5.1)
Requires-Dist: zipp (==3.15.0)
